djaptcha/__init__.py
djaptcha/admin.py
djaptcha/apps.py
djaptcha/forms.py
djaptcha/models.py
djaptcha/tests.py
djaptcha/urls.py
djaptcha/views.py
djaptcha/widgets.py
djaptcha/templates/djaptcha/cookies.html
djaptcha/templates/djaptcha/forms/widgets/captcha.html
djaptcha-0.0.1.dist-info/LICENSE
djaptcha-0.0.1.dist-info/METADATA
djaptcha-0.0.1.dist-info/WHEEL
djaptcha-0.0.1.dist-info/top_level.txt
djaptcha-0.0.1.dist-info/RECORD
