Metadata-Version: 2.1
Name: djaptcha
Version: 0.0.1
Summary: Djaptcha is a Django plugin that implements the captcha python package by lepture.
Home-page: https://github.com/jackno/djaptcha
Author: Jack Novotny
Author-email: jacknovotny8@gmail.com
License: MIT License
Platform: UNKNOWN
Classifier: Environment :: Web Environment
Classifier: Framework :: Django
Classifier: Framework :: Django :: 2.2
Classifier: Intended Audience :: Developers
Classifier: License :: OSI Approved :: MIT License
Classifier: Operating System :: OS Independent
Classifier: Programming Language :: Python
Classifier: Programming Language :: Python :: 3.5
Classifier: Programming Language :: Python :: 3.6
Classifier: Topic :: Internet :: WWW/HTTP
Classifier: Topic :: Internet :: WWW/HTTP :: Dynamic Content
